geoforge/__init__.py
geoforge/geoforge.py
geoforge-0.0.1.dist-info/LICENSE
geoforge-0.0.1.dist-info/METADATA
geoforge-0.0.1.dist-info/WHEEL
geoforge-0.0.1.dist-info/entry_points.txt
geoforge-0.0.1.dist-info/top_level.txt
geoforge-0.0.1.dist-info/RECORD
