Metadata-Version: 2.2
Name: geoforge
Version: 0.0.1
Summary: A comprehensive toolkit for geospatial data processing
Home-page: https://github.com/yourusername/geoforge
Author: Samapriya Roy
Author-email: samapriya.roy@gmail.com
Classifier: Development Status :: 3 - Alpha
Classifier: Intended Audience :: Science/Research
Classifier: Topic :: Scientific/Engineering :: GIS
Classifier: License :: OSI Approved :: MIT License
Classifier: Programming Language :: Python :: 3
Classifier: Programming Language :: Python :: 3.7
Classifier: Programming Language :: Python :: 3.8
Classifier: Programming Language :: Python :: 3.9
Classifier: Programming Language :: Python :: 3.10
Requires-Python: >=3.7
License-File: LICENSE
Requires-Dist: click>=8.1.8
Requires-Dist: rasterio>=1.3.9
Requires-Dist: tqdm>=4.67.1
Dynamic: author
Dynamic: author-email
Dynamic: classifier
Dynamic: description
Dynamic: description-content-type
Dynamic: home-page
Dynamic: requires-dist
Dynamic: requires-python
Dynamic: summary
